newton_usd_schemas/__init__.py
newton_usd_schemas/_version.py
newton_usd_schemas/generatedSchema.usda
newton_usd_schemas/plugInfo.json
newton_usd_schemas-0.1.0a1.dist-info/METADATA
newton_usd_schemas-0.1.0a1.dist-info/WHEEL
newton_usd_schemas-0.1.0a1.dist-info/licenses/LICENSE.md
newton_usd_schemas-0.1.0a1.dist-info/RECORD
