Metadata-Version: 2.4
Name: newton-usd-schemas
Version: 0.1.0a1
Summary: OpenUSD schema definitions for the Newton physics engine
Project-URL: Homepage, https://github.com/newton-physics/newton-usd-schemas
Project-URL: Repository, https://github.com/newton-physics/newton-usd-schemas
Project-URL: Changelog, https://github.com/newton-physics/newton-usd-schemas/blob/main/CHANGELOG.md
Author: Newton Developers
License-Expression: Apache-2.0
License-File: LICENSE.md
Requires-Python: <3.13,>=3.10
